seahorse/__about__.py
seahorse/__init__.py
seahorse/game/__init__.py
seahorse/game/action.py
seahorse/game/custom_stat.py
seahorse/game/game_state.py
seahorse/game/io_stream.py
seahorse/game/master.py
seahorse/game/representation.py
seahorse/game/stateful_action.py
seahorse/game/stateless_action.py
seahorse/game/game_layout/__init__.py
seahorse/game/game_layout/board.py
seahorse/player/__init__.py
seahorse/player/contrainers.py
seahorse/player/player.py
seahorse/player/proxies.py
seahorse/utils/__init__.py
seahorse/utils/custom_exceptions.py
seahorse/utils/gui_client.py
seahorse/utils/recorders.py
seahorse/utils/serializer.py
seahorse-1.2.1.dist-info/METADATA
seahorse-1.2.1.dist-info/WHEEL
seahorse-1.2.1.dist-info/licenses/LICENSE
seahorse-1.2.1.dist-info/RECORD
