Metadata-Version: 2.4
Name: seahorse
Version: 1.2.1
Project-URL: Documentation, https://github.com/corail-research/seahorse#readme
Project-URL: Issues, https://github.com/corail-research/seahorse/issues
Project-URL: Source, https://github.com/corail-research/seahorse
Author-email: Corail-research-group <quentin.cappart@polymtl.ca>
License-Expression: BSD-3-Clause
License-File: LICENSE
Classifier: Development Status :: 4 - Beta
Classifier: Programming Language :: Python
Classifier: Programming Language :: Python :: 3.11
Classifier: Programming Language :: Python :: 3.12
Classifier: Programming Language :: Python :: 3.13
Classifier: Programming Language :: Python :: 3.14
Classifier: Programming Language :: Python :: Implementation :: PyPy
Requires-Python: >=3.11
Requires-Dist: aiohttp
Requires-Dist: aioprocessing[dill]
Requires-Dist: asyncio
Requires-Dist: loguru
Requires-Dist: nest-asyncio
Requires-Dist: python-socketio
Requires-Dist: split
